jancodegen/__init__.py
jancodegen/jan.py
jancodegen-1.0.2.dist-info/METADATA
jancodegen-1.0.2.dist-info/WHEEL
jancodegen-1.0.2.dist-info/top_level.txt
jancodegen-1.0.2.dist-info/RECORD
