Metadata-Version: 2.4
Name: jancodegen
Version: 1.0.2
Summary: A Python package for generating random JAN codes and related product identification codes with valid check digits
Home-page: https://github.com/kientt137/jancodegen
Author: Tran Trung Kien
Author-email: kientt13.7@gmail.com
Requires-Python: >=3.7
Dynamic: author
Dynamic: author-email
Dynamic: description
Dynamic: description-content-type
Dynamic: home-page
Dynamic: requires-python
Dynamic: summary
